{
  "project_info": {
    "project_number": "290483832710",
    "firebase_url": "https://iot-one-3316c-default-rtdb.firebaseio.com",
    "project_id": "iot-one-3316c",
    "storage_bucket": "iot-one-3316c.appspot.com"
  },
  "client": [
    {
      "client_info": {
        "mobilesdk_app_id": "1:290483832710:android:db2df9089d74acbd370e07",
        "android_client_info": {
          "package_name": "com.example.hydroponics"
        }
      },
      "oauth_client": [
        {
          "client_id": "290483832710-kv781iu1apelpu485k1619bvso4a9lqd.apps.googleusercontent.com",
          "client_type": 3
        }
      ],
      "api_key": [
        {
          "current_key": "AIzaSyBbtAHyJQK93IZxy_0MyNxPbzfMsUTfjeg"
        }
      ],
      "services": {
        "appinvite_service": {
          "other_platform_oauth_client": [
            {
              "client_id": "290483832710-kv781iu1apelpu485k1619bvso4a9lqd.apps.googleusercontent.com",
              "client_type": 3
            },
            {
              "client_id": "290483832710-7vp3spgidtefhhmtlb2sohs3adrc9kdf.apps.googleusercontent.com",
              "client_type": 2,
              "ios_info": {
                "bundle_id": "com.example.smartfarm"
              }
            }
          ]
        }
      }
    }
  ],
  "configuration_version": "1"
}